{
"type": "FeatureCollection",
"name": "WestCoast_Rural_2024_2025 - Imagery_Centres",
"crs": { "type": "name", "properties": { "name": "urn:ogc:def:crs:OGC:1.3:CRS84" } },
"xy_coordinate_resolution": 1e-15,
"features": [
{ "type": "Feature", "properties": { "Project": "PGRM3221", "Company_Name": "West Coast RC", "SN_No": "SN14358", "Description": "West Coast Rural - 2025 Flying 16408 ft & orthos", "OrthoGSD_m": 0.2, "PointDensity_(points/m2)": null, "Area": 12709.010393067223, "Percentage_Coverage": 100.0 }, "geometry": { "type": "Point", "coordinates": [ 170.22854000555381, -43.098732077055651 ] } }
]
}
